CHANGES.txt
LICENSE.txt
MANIFEST.in
README.txt
setup.py
js/__init__.py
js.angular_imgcrop.egg-info/PKG-INFO
js.angular_imgcrop.egg-info/SOURCES.txt
js.angular_imgcrop.egg-info/dependency_links.txt
js.angular_imgcrop.egg-info/entry_points.txt
js.angular_imgcrop.egg-info/namespace_packages.txt
js.angular_imgcrop.egg-info/not-zip-safe
js.angular_imgcrop.egg-info/requires.txt
js.angular_imgcrop.egg-info/top_level.txt
js/angular_imgcrop/__init__.py
js/angular_imgcrop/test_ngimgcrop.txt
js/angular_imgcrop/resources/ng-img-crop.css
js/angular_imgcrop/resources/ng-img-crop.js
js/angular_imgcrop/resources/ng-img-crop.min.css
js/angular_imgcrop/resources/ng-img-crop.min.js