Metadata-Version: 1.0
Name: js.angular-imgcrop
Version: 0.3.2
Summary: Fanstatic packaging of ngImgCrop
Home-page: UNKNOWN
Author: Fanstatic Developers
Author-email: fanstatic@googlegroups.com
License: BSD
Platform: UNKNOWN
